PyCompGeomAlgorithms/__init__.py
PyCompGeomAlgorithms/core.py
PyCompGeomAlgorithms/dynamic_hull.py
PyCompGeomAlgorithms/graham.py
PyCompGeomAlgorithms/jarvis.py
PyCompGeomAlgorithms/kd_tree.py
PyCompGeomAlgorithms/preparata.py
PyCompGeomAlgorithms/quickhull.py
tests/__init__.py
tests/algorithms/__init__.py
tests/algorithms/test_dynamic_hull.py
tests/algorithms/test_entities.py
tests/algorithms/test_graham.py
tests/algorithms/test_jarvis.py
tests/algorithms/test_kd_tree.py
tests/algorithms/test_preparata.py
tests/algorithms/test_quickhull.py
tests/entities/__init__.py
tests/entities/test_avl_tree.py
tests/entities/test_bin_tree.py
tests/entities/test_bin_tree_node.py
tests/entities/test_entities.py
tests/entities/test_threaded_bin_tree.py
PyCompGeomAlgorithms-1.0.26.dist-info/LICENSE
PyCompGeomAlgorithms-1.0.26.dist-info/METADATA
PyCompGeomAlgorithms-1.0.26.dist-info/WHEEL
PyCompGeomAlgorithms-1.0.26.dist-info/top_level.txt
PyCompGeomAlgorithms-1.0.26.dist-info/RECORD
