Metadata-Version: 2.1
Name: PyCompGeomAlgorithms
Version: 1.0.26
Summary: An implementation of computational geometry algorithms in Python3.
Author: artandfi (Artem Fisunenko)
Author-email: artyom.fisunenko@gmail.com
Keywords: Python3,computational geometry,convex hull,region search,geometric search,point location,proximity,closest pair,closest points
Classifier: Programming Language :: Python :: 3
Classifier: Operating System :: OS Independent
License-File: LICENSE
